bearwatch/__init__.py
bearwatch/client.py
bearwatch/config.py
bearwatch/errors.py
bearwatch/py.typed
bearwatch/types.py
bearwatch/_internal/__init__.py
bearwatch/_internal/http_client.py
bearwatch/_internal/retry.py
bearwatch-0.1.3.dist-info/METADATA
bearwatch-0.1.3.dist-info/WHEEL
bearwatch-0.1.3.dist-info/RECORD
