Metadata-Version: 2.4
Name: bearwatch
Version: 0.1.3
Summary: BearWatch Python SDK - Job monitoring with heartbeat-based detection
Project-URL: Homepage, https://bearwatch.dev
Project-URL: Documentation, https://docs.bearwatch.dev
Project-URL: Repository, https://github.com/bearwatch/bearwatch-python
Author-email: BearWatch <support@bearwatch.dev>
License: MIT
Keywords: alerting,cron,heartbeat,job,monitoring
Classifier: Development Status :: 4 - Beta
Classifier: Intended Audience :: Developers
Classifier: License :: OSI Approved :: MIT License
Classifier: Programming Language :: Python :: 3
Classifier: Programming Language :: Python :: 3.9
Classifier: Programming Language :: Python :: 3.10
Classifier: Programming Language :: Python :: 3.11
Classifier: Programming Language :: Python :: 3.12
Classifier: Typing :: Typed
Requires-Python: >=3.9
Requires-Dist: httpx>=0.25.0
Provides-Extra: dev
Requires-Dist: pytest-asyncio>=0.21.0; extra == 'dev'
Requires-Dist: pytest>=7.0.0; extra == 'dev'
Requires-Dist: respx>=0.20.0; extra == 'dev'
